blob_your_face/__init__.py
blob_your_face/main.py
blob_your_face-0.1.2.dist-info/METADATA
blob_your_face-0.1.2.dist-info/WHEEL
blob_your_face-0.1.2.dist-info/entry_points.txt
blob_your_face-0.1.2.dist-info/top_level.txt
blob_your_face-0.1.2.dist-info/RECORD
