Metadata-Version: 2.1
Name: blob-your-face
Version: 0.1.2
Summary: A tool to detect faces in images and apply a blob effect
Home-page: https://github.com/crapthings/py-blob-your-face
Author: crapthings
Author-email: crapthings@gmail.com
Keywords: face detection,image processing,blob effect
Classifier: Development Status :: 3 - Alpha
Classifier: Intended Audience :: Developers
Classifier: License :: OSI Approved :: MIT License
Classifier: Operating System :: OS Independent
Classifier: Programming Language :: Python :: 3
Classifier: Programming Language :: Python :: 3.6
Classifier: Programming Language :: Python :: 3.7
Classifier: Programming Language :: Python :: 3.8
Classifier: Programming Language :: Python :: 3.9
Requires-Python: >=3.6
Requires-Dist: opencv-python
Requires-Dist: numpy
Requires-Dist: ultralytics
Requires-Dist: pillow
